[
  {
    "model": "users.user",
    "pk": 1,
    "fields": {
      "password": "pbkdf2_sha256$720000$oor5en76LzZAapxk7K8xpH$1UFbNXE9RsBtg/XCcu4i67orHMc2dPt/PUuY1LBXC5o=",
      "last_login": "2025-03-31T21:43:29.002Z",
      "is_superuser": true,
      "is_staff": true,
      "date_joined": "2025-03-25T00:35:52.058Z",
      "email": "admin@web.top",
      "first_name": "Admin",
      "last_name": "Adminov",
      "phone": null,
      "telegram": null,
      "avatar": "",
      "is_active": true,
      "groups": [],
      "user_permissions": []
    }
  },
  {
    "model": "users.user",
    "pk": 3,
    "fields": {
      "password": "pbkdf2_sha256$720000$7WWXZm9UvJgJRhfpcauy7w$63eZoaxPDypX22Nv6ray6z3gMEWbk6p1OBVFmRQcg9g=",
      "last_login": "2025-04-02T22:35:37.595Z",
      "is_superuser": false,
      "is_staff": false,
      "date_joined": "2025-04-02T02:09:14.625Z",
      "email": "user2@web.top",
      "first_name": "",
      "last_name": "",
      "phone": null,
      "telegram": null,
      "avatar": "",
      "is_active": true,
      "groups": [],
      "user_permissions": []
    }
  },
  {
    "model": "users.user",
    "pk": 4,
    "fields": {
      "password": "pbkdf2_sha256$720000$T1xeBLjdv04v2H1TghpodA$B7G6TnlLtPb3fm1iINYo/XJ/ZPJRjw4qLtPRGlJ4sMA=",
      "last_login": null,
      "is_superuser": false,
      "is_staff": false,
      "date_joined": "2025-04-02T23:37:29.929Z",
      "email": "ryan_gosling@web.top",
      "first_name": "Ryan",
      "last_name": "Gosling",
      "phone": null,
      "telegram": null,
      "avatar": "gosling.jpg",
      "is_active": true,
      "groups": [],
      "user_permissions": []
    }
  }
]